Moirepattern/__init__.py
Moirepattern/constructor.py
Moirepattern/moire.py
Moirepattern/svgop.py
Moirepattern/vis.py
Moirepattern-0.1.2a2.dist-info/LICENSE
Moirepattern-0.1.2a2.dist-info/METADATA
Moirepattern-0.1.2a2.dist-info/WHEEL
Moirepattern-0.1.2a2.dist-info/top_level.txt
Moirepattern-0.1.2a2.dist-info/RECORD
